smtp_logger/__init__.py
smtp_logger/__main__.py
smtp_logger-0.0.1.dist-info/LICENSE
smtp_logger-0.0.1.dist-info/METADATA
smtp_logger-0.0.1.dist-info/WHEEL
smtp_logger-0.0.1.dist-info/entry_points.txt
smtp_logger-0.0.1.dist-info/top_level.txt
smtp_logger-0.0.1.dist-info/RECORD
