Metadata-Version: 2.1
Name: smtp-logger
Version: 0.0.1
Summary: Mock SMTP server that logs the emails it receives
Author-email: Dave Peck <dave@literalgarage.com>
License: MIT
Project-URL: Homepage, https://github.com/literalgarage/smtp-logger
Project-URL: Changelog, https://github.com/literalgarage/smtp-logger/releases
Project-URL: Issues, https://github.com/literalgarage/smtp-logger/issues
Project-URL: CI, https://github.com/literalgarage/smtp-logger/actions
Classifier: License :: OSI Approved :: MIT License
Classifier: Programming Language :: Python :: 3 :: Only
Classifier: Programming Language :: Python :: 3.10
Classifier: Programming Language :: Python :: 3.11
Classifier: Programming Language :: Python :: 3.12
Requires-Python: >=3.10
License-File: LICENSE
Provides-Extra: build
Requires-Dist: setuptools ; extra == 'build'
Requires-Dist: wheel ; extra == 'build'
Requires-Dist: build ; extra == 'build'
Provides-Extra: dev
Requires-Dist: pytest ; extra == 'dev'
Requires-Dist: ruff ; extra == 'dev'
Requires-Dist: mypy ; extra == 'dev'
